loggaby/__init__.py
loggaby-1.1.1.dist-info/LICENSE
loggaby-1.1.1.dist-info/METADATA
loggaby-1.1.1.dist-info/WHEEL
loggaby-1.1.1.dist-info/top_level.txt
loggaby-1.1.1.dist-info/RECORD
