Metadata-Version: 2.1
Name: loggaby
Version: 1.1.1
Summary: 🐍 Simple, minimal and non-bloated logging for Python.
Home-page: https://github.com/Loggaby/Loggaby-py
Author: TorchedSammy
Author-email: torchedsammy@gmail.com
License: UNKNOWN
Platform: UNKNOWN
Classifier: Development Status :: 4 - Beta
Classifier: Environment :: Console
Classifier: Intended Audience :: Developers
Classifier: License :: OSI Approved :: MIT License
Classifier: Programming Language :: Python :: 3
Classifier: Topic :: Software Development :: Libraries :: Python Modules
Classifier: Topic :: System :: Logging
